kapso_whatsapp/__init__.py
kapso_whatsapp/client.py
kapso_whatsapp/exceptions.py
kapso_whatsapp/kapso.py
kapso_whatsapp/types.py
kapso_whatsapp/resources/__init__.py
kapso_whatsapp/resources/base.py
kapso_whatsapp/resources/calls.py
kapso_whatsapp/resources/contacts.py
kapso_whatsapp/resources/conversations.py
kapso_whatsapp/resources/flows.py
kapso_whatsapp/resources/media.py
kapso_whatsapp/resources/messages.py
kapso_whatsapp/resources/phone_numbers.py
kapso_whatsapp/resources/templates.py
kapso_whatsapp/server/__init__.py
kapso_whatsapp/server/flows.py
kapso_whatsapp/webhooks/__init__.py
kapso_whatsapp/webhooks/normalize.py
kapso_whatsapp/webhooks/verify.py
kapso_whatsapp_cloud_api-0.1.4.dist-info/METADATA
kapso_whatsapp_cloud_api-0.1.4.dist-info/WHEEL
kapso_whatsapp_cloud_api-0.1.4.dist-info/licenses/LICENSE
kapso_whatsapp_cloud_api-0.1.4.dist-info/RECORD
