Metadata-Version: 2.4
Name: kapso-whatsapp-cloud-api
Version: 0.1.4
Summary: Python client for WhatsApp Business Cloud API with Pydantic validation and async support
Project-URL: Homepage, https://docs.kapso.ai
Project-URL: Documentation, https://docs.kapso.ai/docs/whatsapp/python-sdk
Project-URL: Repository, https://github.com/gokapso/whatsapp-cloud-api-python
Project-URL: Issues, https://github.com/gokapso/whatsapp-cloud-api-python/issues
Author-email: Kapso <dev@kapso.ai>
License-Expression: MIT
License-File: LICENSE
Keywords: async,cloud-api,kapso,meta,python,sdk,whatsapp,whatsapp-api,whatsapp-business-api,whatsapp-cloud-api
Classifier: Development Status :: 4 - Beta
Classifier: Framework :: AsyncIO
Classifier: Intended Audience :: Developers
Classifier: License :: OSI Approved :: MIT License
Classifier: Operating System :: OS Independent
Classifier: Programming Language :: Python :: 3
Classifier: Programming Language :: Python :: 3.10
Classifier: Programming Language :: Python :: 3.11
Classifier: Programming Language :: Python :: 3.12
Classifier: Programming Language :: Python :: 3.13
Classifier: Topic :: Communications :: Chat
Classifier: Topic :: Software Development :: Libraries :: Python Modules
Classifier: Typing :: Typed
Requires-Python: >=3.10
Requires-Dist: cryptography>=42.0.0
Requires-Dist: httpx>=0.27.0
Requires-Dist: pydantic>=2.0.0
Provides-Extra: dev
Requires-Dist: mypy>=1.10.0; extra == 'dev'
Requires-Dist: pytest-asyncio>=0.24.0; extra == 'dev'
Requires-Dist: pytest-cov>=5.0.0; extra == 'dev'
Requires-Dist: pytest>=8.0.0; extra == 'dev'
Requires-Dist: respx>=0.21.0; extra == 'dev'
Requires-Dist: ruff>=0.5.0; extra == 'dev'
